id_Dodd23/Potential_H99.py
id_Dodd23/__init__.py
id_Dodd23/coordinates.py
id_Dodd23/dynamics.py
id_Dodd23/id_stars.py
id_Dodd23/load_data.py
id_Dodd23/mahalanobis_funcs.py
id_Dodd23/plotting.py
id_Dodd23/data/original_Dodd23_Group_Covar_ELzLp.npy
id_Dodd23/data/original_Dodd23_Group_Mean_ELzLp.npy
id_Dodd23/data/original_Dodd23_Groups.npy
id_Dodd23/data/test_data.csv
id_dodd23-0.2.1.dist-info/METADATA
id_dodd23-0.2.1.dist-info/WHEEL
id_dodd23-0.2.1.dist-info/top_level.txt
id_dodd23-0.2.1.dist-info/RECORD
