Metadata-Version: 2.4
Name: id_Dodd23
Version: 0.2.1
Summary: A package to classify halo stars into Dodd23 groups.
Author-email: Tom Callingham <tom.m.callingham@gmail.com>
Classifier: Programming Language :: Python :: 3
Classifier: License :: OSI Approved :: MIT License
Classifier: Operating System :: OS Independent
Requires-Dist: numpy
Requires-Dist: astropy
